birre/__init__.py
birre/_fastmcp_env.py
birre/mcp_metadata.json
birre/py.typed
birre/application/__init__.py
birre/application/diagnostics.py
birre/application/offline_samples.py
birre/application/server.py
birre/application/startup.py
birre/cli/__init__.py
birre/cli/app.py
birre/cli/formatting.py
birre/cli/invocation.py
birre/cli/main.py
birre/cli/models.py
birre/cli/runtime.py
birre/cli/sync_bridge.py
birre/cli/validation.py
birre/cli/commands/__init__.py
birre/cli/commands/config.py
birre/cli/commands/logs.py
birre/cli/commands/run.py
birre/cli/commands/selftest/__init__.py
birre/cli/commands/selftest/command.py
birre/cli/commands/selftest/rendering.py
birre/cli/commands/selftest/runner.py
birre/cli/options/__init__.py
birre/cli/options/auth_runtime.py
birre/cli/options/core.py
birre/cli/options/logging.py
birre/config/__init__.py
birre/config/constants.py
birre/config/settings.py
birre/domain/__init__.py
birre/domain/common.py
birre/domain/selftest_models.py
birre/domain/subscription.py
birre/domain/company_rating/__init__.py
birre/domain/company_rating/constants.py
birre/domain/company_rating/service.py
birre/domain/company_search/__init__.py
birre/domain/company_search/service.py
birre/domain/folders/utils.py
birre/domain/risk_manager/__init__.py
birre/domain/risk_manager/service.py
birre/infrastructure/__init__.py
birre/infrastructure/errors.py
birre/infrastructure/logging.py
birre/integrations/__init__.py
birre/integrations/bitsight/__init__.py
birre/integrations/bitsight/client.py
birre/integrations/bitsight/v1_bridge.py
birre/resources/__init__.py
birre/resources/apis/bitsight.v1.schema.json
birre/resources/apis/bitsight.v2.schema.json
birre-4.0.0.dist-info/licenses/LICENSE
birre-4.0.0.dist-info/METADATA
birre-4.0.0.dist-info/WHEEL
birre-4.0.0.dist-info/entry_points.txt
birre-4.0.0.dist-info/top_level.txt
birre-4.0.0.dist-info/RECORD
