Metadata-Version: 2.4
Name: BiRRe
Version: 4.0.0
Summary: Model Context Protocol server for BitSight security ratings
Author: boecht
License-Expression: Unlicense
Project-URL: repository, https://github.com/boecht/birre
Keywords: bitsight,cybersecurity,fastmcp,llm-tools,mcp,model-context-protocol,risk-management,security-ratings
Classifier: Development Status :: 4 - Beta
Classifier: Environment :: Console
Classifier: Environment :: Plugins
Classifier: Framework :: AsyncIO
Classifier: Framework :: Pydantic :: 2
Classifier: Intended Audience :: Financial and Insurance Industry
Classifier: Intended Audience :: Information Technology
Classifier: Natural Language :: English
Classifier: Operating System :: OS Independent
Classifier: Programming Language :: Python :: 3
Classifier: Programming Language :: Python :: 3 :: Only
Classifier: Programming Language :: Python :: 3.13
Classifier: Topic :: Office/Business :: Financial :: Investment
Classifier: Topic :: Security
Classifier: Typing :: Typed
Requires-Python: >=3.13
License-File: LICENSE
Requires-Dist: dynaconf<4,>=3.2.3
Requires-Dist: fastmcp<3,>=2.13.0
Requires-Dist: httpx<0.29,>=0.24.0
Requires-Dist: openapi-spec-validator<0.8,>=0.7.1
Requires-Dist: prance>=23.6.7
Requires-Dist: pydantic<3,>=2.12.0
Requires-Dist: python-dotenv<2,>=1.1.0
Requires-Dist: rich>=13.7.0
Requires-Dist: structlog>=24.1.0
Requires-Dist: typer>=0.12.3
Requires-Dist: typing_extensions>=4.9.0
Provides-Extra: pytest-dependencies
Requires-Dist: pytest>=8.3.0; extra == "pytest-dependencies"
Requires-Dist: pytest-asyncio>=0.24.0; extra == "pytest-dependencies"
Requires-Dist: pytest-cov>=5.0.0; extra == "pytest-dependencies"
Requires-Dist: pytest-mock>=3.12.0; extra == "pytest-dependencies"
Dynamic: license-file
